README.md
setup.cfg
setup.py
image_printer/__init__.py
image_printer.egg-info/PKG-INFO
image_printer.egg-info/SOURCES.txt
image_printer.egg-info/dependency_links.txt
image_printer.egg-info/requires.txt
image_printer.egg-info/top_level.txt