Metadata-Version: 1.2
Name: image-printer
Version: 0.0.1
Summary: stdout image as colored text
Home-page: https://github.com/Zzznorlax/image-printer
License: UNKNOWN
Platform: UNKNOWN
Classifier: Programming Language :: Python :: 3
Classifier: License :: OSI Approved :: MIT License
Classifier: Operating System :: OS Independent
Requires-Python: >=3.8
